concurrex/__init__.py
concurrex/_thread.py
concurrex/_thread_concurrent.py
concurrex/_thread_exe.py
concurrex/_thread_pool.py
concurrex/py.typed
concurrex/thread.py
concurrex/thread_utils.py
concurrex/utils.py
concurrex-0.0.2.dist-info/licenses/LICENSE
concurrex-0.0.2.dist-info/WHEEL
concurrex-0.0.2.dist-info/METADATA
concurrex-0.0.2.dist-info/RECORD
