Metadata-Version: 2.4
Name: concurrex
Version: 0.0.2
Summary: Python concurrent execution helpers
Author-email: Dobatymo <dobatymo@users.noreply.github.com>
Requires-Python: >=3.8
Classifier: License :: OSI Approved :: MIT License
Classifier: Programming Language :: Python :: 3 :: Only
Classifier: Programming Language :: Python :: 3.8
Classifier: Programming Language :: Python :: 3.9
Classifier: Programming Language :: Python :: 3.10
Classifier: Programming Language :: Python :: 3.11
Classifier: Programming Language :: Python :: 3.12
License-File: LICENSE
Requires-Dist: genutility[callbacks, concurrency, time]>=0.0.117
Requires-Dist: rich
Requires-Dist: typing-extensions>=4
Requires-Dist: atomicarray>=0.0.1 ; extra == "fast"
Project-URL: Home, https://github.com/Dobatymo/concurrex
Provides-Extra: fast
